pylabeador/__init__.py
pylabeador/__main__.py
pylabeador/__version__.py
pylabeador/errors.py
pylabeador/models.py
pylabeador/pylabeador.py
pylabeador/syllabify.py
pylabeador/util.py
pylabeador-0.8.2.dist-info/METADATA
pylabeador-0.8.2.dist-info/WHEEL
pylabeador-0.8.2.dist-info/entry_points.txt
pylabeador-0.8.2.dist-info/licenses/COPYING
pylabeador-0.8.2.dist-info/RECORD
